jabbatron
