Metadata-Version: 1.1
Name: jabbatron
Version: 0.4.0
Summary: Interactive installer script for Ubuntu.
Home-page: https://github.com/jabbalaci/jabbatron
Author: Laszlo Szathmary
Author-email: jabba.laci@gmail.com
License: GPLv3
Keywords: jabba,installer,ubuntu
Platform: Linux
Classifier: Development Status :: 4 - Beta
Classifier: Intended Audience :: System Administrators
Classifier: Natural Language :: English
Classifier: License :: OSI Approved :: GNU General Public License (GPL)
Classifier: Programming Language :: Python
Classifier: Programming Language :: Python :: 2
Classifier: Programming Language :: Python :: 2.7
Classifier: Operating System :: POSIX :: Linux
Classifier: Topic :: Utilities
